[
	{
		"name": "Java 17"
	},
	{
		"sha1sum": "7bba19e34be22fded9ceb409ca1e8fb7525daf55",
		"name": "authlib-3.2.38.jar",
		"url": "https://libraries.minecraft.net/com/mojang/authlib/3.2.38/authlib-3.2.38.jar"
	},
	{
		"sha1sum": "7039c2c6209064ee4132cea7a0737b63b92c725e",
		"name": "blocklist-1.0.6.jar",
		"url": "https://libraries.minecraft.net/com/mojang/blocklist/1.0.6/blocklist-1.0.6.jar"
	},
	{
		"sha1sum": "c1ef1234282716483c92183f49bef47b1a89bfa9",
		"name": "brigadier-1.0.18.jar",
		"url": "https://libraries.minecraft.net/com/mojang/brigadier/1.0.18/brigadier-1.0.18.jar"
	},
	{
		"sha1sum": "49d94806b6e3dc933dacbd8acb0fdbab8ebd1e5d",
		"name": "commons-codec-1.15.jar",
		"url": "https://libraries.minecraft.net/commons-codec/commons-codec/1.15/commons-codec-1.15.jar"
	},
	{
		"sha1sum": "4ec95b60d4e86b5c95a0e919cb172a0af98011ef",
		"name": "commons-compress-1.21.jar",
		"url": "https://libraries.minecraft.net/org/apache/commons/commons-compress/1.21/commons-compress-1.21.jar"
	},
	{
		"sha1sum": "a2503f302b11ebde7ebc3df41daebe0e4eea3689",
		"name": "commons-io-2.11.0.jar",
		"url": "https://libraries.minecraft.net/commons-io/commons-io/2.11.0/commons-io-2.11.0.jar"
	},
	{
		"sha1sum": "c6842c86792ff03b9f1d1fe2aab8dc23aa6c6f0e",
		"name": "commons-lang3-3.12.0.jar",
		"url": "https://libraries.minecraft.net/org/apache/commons/commons-lang3/3.12.0/commons-lang3-3.12.0.jar"
	},
	{
		"sha1sum": "4bfc12adfe4842bf07b657f0369c4cb522955686",
		"name": "commons-logging-1.2.jar",
		"url": "https://libraries.minecraft.net/commons-logging/commons-logging/1.2/commons-logging-1.2.jar"
	},
	{
		"sha1sum": "ebd6690f33871ccee9b6132c6480668ee2e35020",
		"name": "datafixerupper-4.0.26.jar",
		"url": "https://libraries.minecraft.net/com/mojang/datafixerupper/4.0.26/datafixerupper-4.0.26.jar"
	},
	{
		"sha1sum": "1dcf1de382a0bf95a3d8b0849546c88bac1292c9",
		"name": "failureaccess-1.0.1.jar",
		"url": "https://libraries.minecraft.net/com/google/guava/failureaccess/1.0.1/failureaccess-1.0.1.jar"
	},
	{
		"sha1sum": "76f95700418a68fbc4ac050525261f05dc681ca1",
		"name": "fastutil-8.5.6.jar",
		"url": "https://libraries.minecraft.net/it/unimi/dsi/fastutil/8.5.6/fastutil-8.5.6.jar"
	},
	{
		"sha1sum": "8a432c1d6825781e21a02db2e2c33c5fde2833b9",
		"name": "gson-2.8.9.jar",
		"url": "https://libraries.minecraft.net/com/google/code/gson/gson/2.8.9/gson-2.8.9.jar"
	},
	{
		"sha1sum": "119ea2b2bc205b138974d351777b20f02b92704b",
		"name": "guava-31.0.1-jre.jar",
		"url": "https://libraries.minecraft.net/com/google/guava/guava/31.0.1-jre/guava-31.0.1-jre.jar"
	},
	{
		"sha1sum": "e5f6cae5ca7ecaac1ec2827a9e2d65ae2869cada",
		"name": "httpclient-4.5.13.jar",
		"url": "https://libraries.minecraft.net/org/apache/httpcomponents/httpclient/4.5.13/httpclient-4.5.13.jar"
	},
	{
		"sha1sum": "9dd1a631c082d92ecd4bd8fd4cf55026c720a8c1",
		"name": "httpcore-4.4.14.jar",
		"url": "https://libraries.minecraft.net/org/apache/httpcomponents/httpcore/4.4.14/httpcore-4.4.14.jar"
	},
	{
		"sha1sum": "dfa3a1fbc55bf5db8c6e79fc0935ac7ab1202950",
		"name": "icu4j-70.1.jar",
		"url": "https://libraries.minecraft.net/com/ibm/icu/icu4j/70.1/icu4j-70.1.jar"
	},
	{
		"sha1sum": "0c876796229b2ef5120f186eab5acc870699d3b9",
		"name": "javabridge-1.2.24.jar",
		"url": "https://libraries.minecraft.net/com/mojang/javabridge/1.2.24/javabridge-1.2.24.jar"
	},
	{
		"sha1sum": "6ef160c3133a78de015830860197602ca1c855d3",
		"name": "java-objc-bridge-1.0.0.jar",
		"url": "https://libraries.minecraft.net/ca/weblite/java-objc-bridge/1.0.0/java-objc-bridge-1.0.0.jar"
	},
	{
		"sha1sum": "7cf4c87dd802db50721db66947aa237d7ad09418",
		"name": "jna-5.10.0.jar",
		"url": "https://libraries.minecraft.net/net/java/dev/jna/jna/5.10.0/jna-5.10.0.jar"
	},
	{
		"sha1sum": "fbed7d9669dba47714ad0d4f4454290a997aee69",
		"name": "jna-platform-5.10.0.jar",
		"url": "https://libraries.minecraft.net/net/java/dev/jna/jna-platform/5.10.0/jna-platform-5.10.0.jar"
	},
	{
		"sha1sum": "4fdac2fbe92dfad86aa6e9301736f6b4342a3f5c",
		"name": "jopt-simple-5.0.4.jar",
		"url": "https://libraries.minecraft.net/net/sf/jopt-simple/jopt-simple/5.0.4/jopt-simple-5.0.4.jar"
	},
	{
		"sha1sum": "4727d93a76616ffc4149dffac5801827c0f4ac71",
		"name": "log4j-api-2.16.0.jar",
		"url": "https://libraries.minecraft.net/org/apache/logging/log4j/log4j-api/2.16.0/log4j-api-2.16.0.jar"
	},
	{
		"sha1sum": "ca12fb3902ecfcba1e1357ebfc55407acec30ede",
		"name": "log4j-core-2.16.0.jar",
		"url": "https://libraries.minecraft.net/org/apache/logging/log4j/log4j-core/2.16.0/log4j-core-2.16.0.jar"
	},
	{
		"sha1sum": "9264545adfac3d41bba0c269fc5578274c3b5cfa",
		"name": "log4j-slf4j18-impl-2.16.0.jar",
		"url": "https://libraries.minecraft.net/org/apache/logging/log4j/log4j-slf4j18-impl/2.16.0/log4j-slf4j18-impl-2.16.0.jar"
	},
	{
		"sha1sum": "2bb514e444994c6fece99a21f76e0c90438e377f",
		"name": "lwjgl-3.2.1.jar",
		"url": "https://libraries.minecraft.net/org/lwjgl/lwjgl/3.2.1/lwjgl-3.2.1.jar"
	},
	{
		"sha1sum": "8ad6294407e15780b43e84929c40e4c5e997972e",
		"name": "lwjgl-3.2.2.jar",
		"url": "https://libraries.minecraft.net/org/lwjgl/lwjgl/3.2.2/lwjgl-3.2.2.jar"
	},
	{
		"sha1sum": "027abb7f64894b61cad163791acd8113f0b21296",
		"name": "lwjgl-glfw-3.2.1.jar",
		"url": "https://libraries.minecraft.net/org/lwjgl/lwjgl-glfw/3.2.1/lwjgl-glfw-3.2.1.jar"
	},
	{
		"sha1sum": "d3ad4df38e400b8afba1de63f84338809399df5b",
		"name": "lwjgl-glfw-3.2.2.jar",
		"url": "https://libraries.minecraft.net/org/lwjgl/lwjgl-glfw/3.2.2/lwjgl-glfw-3.2.2.jar"
	},
	{
		"sha1sum": "7a0c583fcbec32b15784f846df536e1837d83666",
		"name": "lwjgl-jemalloc-3.2.1.jar",
		"url": "https://libraries.minecraft.net/org/lwjgl/lwjgl-jemalloc/3.2.1/lwjgl-jemalloc-3.2.1.jar"
	},
	{
		"sha1sum": "ee8e57a79300f78294576d87c4a587f8c99402e2",
		"name": "lwjgl-jemalloc-3.2.2.jar",
		"url": "https://libraries.minecraft.net/org/lwjgl/lwjgl-jemalloc/3.2.2/lwjgl-jemalloc-3.2.2.jar"
	},
	{
		"sha1sum": "dc7ff2dabb40a141ee9bf2e326d9b1b19f3278fb",
		"name": "lwjgl-openal-3.2.1.jar",
		"url": "https://libraries.minecraft.net/org/lwjgl/lwjgl-openal/3.2.1/lwjgl-openal-3.2.1.jar"
	},
	{
		"sha1sum": "2b772a102b0a11ee5f2109a5b136f4dc7c630827",
		"name": "lwjgl-openal-3.2.2.jar",
		"url": "https://libraries.minecraft.net/org/lwjgl/lwjgl-openal/3.2.2/lwjgl-openal-3.2.2.jar"
	},
	{
		"sha1sum": "57008c2374c5bc434b18adfef3f3653ee450ee18",
		"name": "lwjgl-opengl-3.2.1.jar",
		"url": "https://libraries.minecraft.net/org/lwjgl/lwjgl-opengl/3.2.1/lwjgl-opengl-3.2.1.jar"
	},
	{
		"sha1sum": "6ac5bb88b44c43ea195a570aab059f63da004cd8",
		"name": "lwjgl-opengl-3.2.2.jar",
		"url": "https://libraries.minecraft.net/org/lwjgl/lwjgl-opengl/3.2.2/lwjgl-opengl-3.2.2.jar"
	},
	{
		"sha1sum": "31f5eb5fce3791d58ec898bc5c1867d76d781ba1",
		"name": "lwjgl-stb-3.2.1.jar",
		"url": "https://libraries.minecraft.net/org/lwjgl/lwjgl-stb/3.2.1/lwjgl-stb-3.2.1.jar"
	},
	{
		"sha1sum": "3b8e6ebc5851dd3d17e37e5cadce2eff2a429f0f",
		"name": "lwjgl-stb-3.2.2.jar",
		"url": "https://libraries.minecraft.net/org/lwjgl/lwjgl-stb/3.2.2/lwjgl-stb-3.2.2.jar"
	},
	{
		"sha1sum": "259f1dbddb921e27e01b32458d6f584eb8bba13a",
		"name": "lwjgl-tinyfd-3.2.1.jar",
		"url": "https://libraries.minecraft.net/org/lwjgl/lwjgl-tinyfd/3.2.1/lwjgl-tinyfd-3.2.1.jar"
	},
	{
		"sha1sum": "fcbe606c8f8da6f8f9a05e2c540eb1ee8632b0e9",
		"name": "lwjgl-tinyfd-3.2.2.jar",
		"url": "https://libraries.minecraft.net/org/lwjgl/lwjgl-tinyfd/3.2.2/lwjgl-tinyfd-3.2.2.jar"
	},
	{
		"sha1sum": "b8266a3c93c1c051109f71d3449e5dcd5d60b333",
		"name": "netty-all-4.1.68.Final.jar",
		"url": "https://libraries.minecraft.net/io/netty/netty-all/4.1.68.Final/netty-all-4.1.68.Final.jar"
	},
	{
		"sha1sum": "1d0ec654d820741327f5a9229d513732a4b7ce50",
		"name": "oshi-core-5.8.5.jar",
		"url": "https://libraries.minecraft.net/com/github/oshi/oshi-core/5.8.5/oshi-core-5.8.5.jar"
	},
	{
		"sha1sum": "ce112c16c6275fdfff2d30208533ec906a191f71",
		"name": "patchy-2.1.6.jar",
		"url": "https://libraries.minecraft.net/com/mojang/patchy/2.1.6/patchy-2.1.6.jar"
	},
	{
		"sha1sum": "83b0359d847ee053d745be7ec0d8e9e8a44304b4",
		"name": "slf4j-api-1.8.0-beta4.jar",
		"url": "https://libraries.minecraft.net/org/slf4j/slf4j-api/1.8.0-beta4/slf4j-api-1.8.0-beta4.jar"
	},
	{
		"sha1sum": "f378f889797edd7df8d32272c06ca80a1b6b0f58",
		"name": "text2speech-1.11.3.jar",
		"url": "https://libraries.minecraft.net/com/mojang/text2speech/1.11.3/text2speech-1.11.3.jar"
	}
]